graph_thanhchinh/__init__.py
graph_thanhchinh/algorithms.py
graph_thanhchinh/graph.py
graph_thanhchinh/image.py
graph_thanhchinh/models.py
graph_thanhchinh-0.1.11.dist-info/licenses/LICENSE
graph_thanhchinh-0.1.11.dist-info/METADATA
graph_thanhchinh-0.1.11.dist-info/WHEEL
graph_thanhchinh-0.1.11.dist-info/top_level.txt
graph_thanhchinh-0.1.11.dist-info/RECORD
